<?xml version="1.0" encoding="UTF-8"?><record_update table="question_choice">
    <question_choice action="INSERT_OR_UPDATE">
        <misc>0</misc>
        <order>300</order>
        <question display_value="Time Zone:">4faa2489075ae01044d0f19d7c1ed0d9</question>
        <rec_misc>0</rec_misc>
        <sys_class_name>question_choice</sys_class_name>
        <sys_created_by>admin</sys_created_by>
        <sys_created_on>2021-02-11 05:50:51</sys_created_on>
        <sys_id>dd21784d075ae01044d0f19d7c1ed031</sys_id>
        <sys_mod_count>0</sys_mod_count>
        <sys_name>Canada/Eastern</sys_name>
        <sys_package display_value="SNOW Evaluation" source="x_572081_snow_eval">b9411cc5071ae01044d0f19d7c1ed039</sys_package>
        <sys_policy/>
        <sys_scope display_value="SNOW Evaluation">b9411cc5071ae01044d0f19d7c1ed039</sys_scope>
        <sys_update_name>question_choice_dd21784d075ae01044d0f19d7c1ed031</sys_update_name>
        <sys_updated_by>admin</sys_updated_by>
        <sys_updated_on>2021-02-11 05:50:51</sys_updated_on>
        <text>Canada/Eastern</text>
        <value>Canada/Eastern</value>
    </question_choice>
    <fx_price action="delete_multiple" query="id=dd21784d075ae01044d0f19d7c1ed031"/>
    <fx_price action="INSERT_OR_UPDATE">
        <amount>0</amount>
        <currency display_value="USD">USD</currency>
        <field>misc</field>
        <id>dd21784d075ae01044d0f19d7c1ed031</id>
        <parent/>
        <reference_amount>0</reference_amount>
        <reference_currency display_value="USD">USD</reference_currency>
        <sys_created_by>admin</sys_created_by>
        <sys_created_on>2021-02-11 05:50:51</sys_created_on>
        <sys_id>bf21348d075ae01044d0f19d7c1ed0e4</sys_id>
        <sys_mod_count>0</sys_mod_count>
        <sys_updated_by>admin</sys_updated_by>
        <sys_updated_on>2021-02-11 05:50:51</sys_updated_on>
        <table>question_choice</table>
        <type>calculated</type>
    </fx_price>
    <fx_price action="INSERT_OR_UPDATE">
        <amount>0</amount>
        <currency display_value="USD">USD</currency>
        <field>rec_misc</field>
        <id>dd21784d075ae01044d0f19d7c1ed031</id>
        <parent/>
        <reference_amount>0</reference_amount>
        <reference_currency display_value="USD">USD</reference_currency>
        <sys_created_by>admin</sys_created_by>
        <sys_created_on>2021-02-11 05:50:51</sys_created_on>
        <sys_id>7721348d075ae01044d0f19d7c1ed0e4</sys_id>
        <sys_mod_count>0</sys_mod_count>
        <sys_updated_by>admin</sys_updated_by>
        <sys_updated_on>2021-02-11 05:50:51</sys_updated_on>
        <table>question_choice</table>
        <type>calculated</type>
    </fx_price>
</record_update>
